{"info":{"frame":47,"view":5,"img_key":"C:\\furun\\furun_second\\img\\Dumbbell_bent-over_lateral_raise_D_cam5_47.png","name":"Dumbbell_bent-over_lateral_raise","standing":3,"pose":2,"grip":1,"e_point":"Shoulder","index":47,"conditions":"D","desc":"Lift the handles laterally to the ceiling until shoulder level by raising your arms while keeping your elbows locked.","bones":{"nose":"690.137, 411.844, 0.7972","left_eye":"698.032, 400.2, 0.104987","right_eye":"684.289, 400.181, 0.883062","left_ear":"0, 0, 0","right_ear":"664.665, 382.484, 0.925445","left_shoulder":"680.241, 372.757, 0.641318","right_shoulder":"617.642, 384.449, 0.82501","left_elbow":"711.602, 382.434, 0.670489","right_elbow":"558.823, 409.939, 0.858064","left_wrist":"744.932, 396.244, 0.774567","right_wrist":"556.835, 449.118, 0.939336","left_hip":"615.594, 443.212, 0.737071","right_hip":"572.557, 445.176, 0.794941","left_knee":"635.168, 509.792, 0.904716","right_knee":"584.308, 523.499, 0.845553","left_ankle":"631.339, 588.271, 0.860728","right_ankle":"586.365, 609.764, 0.838246","neck":"646.996, 382.442, 0.83904","left_palm":"556.835, 449.118, 0.939336","right_palm":"744.932, 396.244, 0.774567","back":"592.152, 443.282, 0.777378","waist":"592.152, 443.282, 0.777378","left_foot":"660.736, 611.712, 0.739353","right_foot":"607.861, 635.336, 0.792686"},"width":1920,"height":1080}}