{"info":{"frame":31,"view":2,"img_key":"C:\\furun\\furun_second\\img\\Arnold_press_D_cam2_31.png","name":"Arnold_press","standing":0,"pose":12,"grip":1,"e_point":"Shoulder","index":31,"conditions":"D","desc":"Push the handles above your head by extending your elbows while bringing the handles together.","bones":{"nose":"709.706, 235.619, 0.112358","left_eye":"0, 0, 0","right_eye":"699.971, 231.713, 0.100427","left_ear":"682.244, 257.086, 0.166846","right_ear":"699.962, 245.394, 0.575065","left_shoulder":"670.548, 268.89, 0.781657","right_shoulder":"729.289, 261.11, 0.847198","left_elbow":"682.248, 210.078, 0.78654","right_elbow":"746.997, 208.104, 0.77942","left_wrist":"694.044, 151.329, 0.843256","right_wrist":"756.693, 147.468, 0.826461","left_hip":"682.367, 382.58, 0.706225","right_hip":"727.279, 384.537, 0.728322","left_knee":"678.322, 460.862, 0.760318","right_knee":"713.702, 468.753, 0.725239","left_ankle":"666.554, 527.525, 0.754539","right_ankle":"711.583, 545.157, 0.767583","neck":"699.893, 264.959, 0.863635","left_palm":"756.693, 147.468, 0.826461","right_palm":"694.044, 151.329, 0.843256","back":"705.766, 384.461, 0.710602","waist":"705.766, 384.461, 0.710602","left_foot":"686.175, 537.241, 0.171187","right_foot":"733.199, 551.043, 0.375872"},"width":1920,"height":1080}}