{"info":{"frame":14,"view":1,"img_key":"C:\\furun\\furun_third\\img\\Seated_fly_D_cam1_14.png","name":"Seated_fly","standing":2,"pose":13,"grip":1,"e_point":"Chest","index":14,"conditions":"D","desc":"Return the handles back to the starting position in a controlled manner.","bones":{"nose":"0, 0, 0","left_eye":"0, 0, 0","right_eye":"0, 0, 0","left_ear":"856.948, 456.697, 0.974111","right_ear":"906.952, 456.551, 0.415975","left_shoulder":"839.433, 524.421, 0.842723","right_shoulder":"930.506, 509.639, 0.916355","left_elbow":"762.875, 565.602, 0.888562","right_elbow":"962.977, 530.37, 0.823858","left_wrist":"692.183, 530.21, 0.899712","right_wrist":"998.212, 486.169, 0.824955","left_hip":"859.994, 668.562, 0.764452","right_hip":"915.899, 668.681, 0.784119","left_knee":"777.539, 659.835, 0.797055","right_knee":"857.015, 648.022, 0.494747","left_ankle":"789.406, 765.685, 0.909145","right_ankle":"857.11, 753.957, 0.686303","neck":"883.515, 515.569, 0.876012","left_palm":"998.212, 486.169, 0.824955","right_palm":"692.183, 530.21, 0.899712","back":"889.312, 668.625, 0.832059","waist":"889.312, 668.625, 0.832059","left_foot":"762.736, 765.788, 0.817283","right_foot":"833.45, 753.948, 0.317275"},"width":1920,"height":1080}}