{"info":{"frame":8,"view":1,"img_key":"C:\\furun\\furun_third\\img\\Seated_fly_D_cam1_08.png","name":"Seated_fly","standing":2,"pose":13,"grip":1,"e_point":"Chest","index":8,"conditions":"D","desc":"Return the handles back to the starting position in a controlled manner.","bones":{"nose":"0, 0, 0","left_eye":"0, 0, 0","right_eye":"0, 0, 0","left_ear":"854.098, 456.676, 0.948416","right_ear":"904.064, 453.64, 0.478348","left_shoulder":"839.437, 524.31, 0.84666","right_shoulder":"930.503, 506.876, 0.926806","left_elbow":"795.179, 594.95, 0.845005","right_elbow":"986.455, 559.701, 0.846324","left_wrist":"733.36, 592.039, 0.780728","right_wrist":"1051.32, 550.71, 0.867386","left_hip":"859.908, 668.599, 0.777022","right_hip":"915.813, 671.507, 0.781069","left_knee":"783.324, 665.55, 0.83698","right_knee":"854.066, 642.157, 0.524089","left_ankle":"789.34, 762.893, 0.92804","right_ankle":"859.865, 745.193, 0.800727","neck":"883.534, 512.626, 0.898368","left_palm":"1051.32, 550.71, 0.867386","right_palm":"733.36, 592.039, 0.780728","back":"886.43, 668.71, 0.831831","waist":"886.43, 668.71, 0.831831","left_foot":"762.715, 765.67, 0.813407","right_foot":"833.432, 745.118, 0.444474"},"width":1920,"height":1080}}