{"info":{"frame":36,"view":1,"img_key":"C:\\furun\\furun_second\\img\\Back_lunge_D_cam1_36.png","name":"Back_lunge","standing":0,"pose":1,"grip":1,"e_point":"Hip, Leg","index":36,"conditions":"D","desc":"Lift the bar by extending your knees and hips while bringing your rear leg forward to the standing position.","bones":{"nose":"0, 0, 0","left_eye":"554.855, 329.634, 0.0859504","right_eye":"0, 0, 0","left_ear":"558.819, 335.447, 0.925721","right_ear":"590.18, 323.746, 0.254909","left_shoulder":"568.625, 372.77, 0.840343","right_shoulder":"627.395, 355.171, 0.82665","left_elbow":"554.841, 429.55, 0.958806","right_elbow":"664.707, 396.278, 0.946996","left_wrist":"525.554, 386.444, 0.917389","right_wrist":"648.976, 353.25, 0.852087","left_hip":"603.984, 488.28, 0.708821","right_hip":"649.011, 478.56, 0.792456","left_knee":"568.61, 492.169, 0.822053","right_knee":"660.736, 552.997, 0.750025","left_ankle":"617.639, 554.964, 0.824635","right_ankle":"711.664, 566.663, 0.741092","neck":"596.077, 366.869, 0.882743","left_palm":"648.976, 353.25, 0.852087","right_palm":"525.554, 386.444, 0.917389","back":"629.331, 482.418, 0.729015","waist":"629.331, 482.418, 0.729015","left_foot":"592.138, 566.691, 0.388707","right_foot":"717.556, 607.859, 0.65321"},"width":1920,"height":1080}}