{"info":{"frame":23,"view":2,"img_key":"C:\\furun\\furun_second\\img\\Arnold_press_A_cam2_23.png","name":"Arnold_press","standing":0,"pose":12,"grip":1,"e_point":"Shoulder","index":23,"conditions":"A","desc":"Stand with your feet shoulder width holding the handles with an under-grip.","bones":{"nose":"0, 0, 0","left_eye":"0, 0, 0","right_eye":"723.442, 223.871, 0.0852403","left_ear":"680.338, 229.792, 0.259943","right_ear":"711.714, 227.756, 0.953659","left_shoulder":"666.614, 261.101, 0.871287","right_shoulder":"721.471, 259.124, 0.78881","left_elbow":"680.374, 196.447, 0.801085","right_elbow":"733.212, 204.22, 0.740818","left_wrist":"686.161, 147.469, 0.885498","right_wrist":"729.356, 147.329, 0.883153","left_hip":"682.197, 380.55, 0.731422","right_hip":"719.506, 382.546, 0.723747","left_knee":"674.42, 460.922, 0.807315","right_knee":"713.609, 470.68, 0.830967","left_ankle":"664.606, 531.407, 0.762745","right_ankle":"711.604, 549.09, 0.80078","neck":"696.059, 259.119, 0.919535","left_palm":"729.356, 147.329, 0.883153","right_palm":"686.161, 147.469, 0.885498","back":"698.05, 382.475, 0.76363","waist":"698.05, 382.475, 0.76363","left_foot":"686.206, 539.185, 0.398666","right_foot":"729.354, 552.95, 0.562814"},"width":1920,"height":1080}}