{"info":{"frame":32,"view":5,"img_key":"C:\\furun\\furun_third\\img\\V-ups_C_cam5_32.png","name":"V-ups","standing":0,"pose":0,"grip":1,"e_point":"Ab","index":32,"conditions":"C","desc":"Bring your hands and feet together by rolling up your torso and lifting your legs simulataneously.","bones":{"nose":"833.409, 594.993, 0.258815","left_eye":"833.339, 594.991, 0.0988228","right_eye":"827.55, 595.067, 0.318698","left_ear":"0, 0, 0","right_ear":"815.758, 618.589, 0.327002","left_shoulder":"0, 0, 0","right_shoulder":"833.373, 630.362, 0.623886","left_elbow":"0, 0, 0","right_elbow":"871.711, 580.379, 0.699028","left_wrist":"0, 0, 0","right_wrist":"927.653, 527.284, 0.627374","left_hip":"983.527, 627.438, 0.291139","right_hip":"983.518, 677.457, 0.456686","left_knee":"1004.12, 524.419, 0.282398","right_knee":"983.578, 524.402, 0.429901","left_ankle":"1042.38, 418.474, 0.228347","right_ankle":"1045.34, 427.318, 0.487192","neck":"854.007, 627.372, 0.507125","left_palm":"927.653, 527.284, 0.627374","right_palm":"0, 0, 0","back":"986.467, 656.827, 0.422509","waist":"986.467, 656.827, 0.422509","left_foot":"0, 0, 0","right_foot":"1054.16, 362.58, 0.319538"},"width":1920,"height":1080}}