{"info":{"frame":56,"view":4,"img_key":"C:\\furun\\furun_third\\img\\Seated_shoulder_press_D_cam4_56.png","name":"Seated_shoulder_press","standing":2,"pose":12,"grip":1,"e_point":"Shoulder","index":56,"conditions":"D","desc":"Lower the bar back to the starting position in a controlled manner.","bones":{"nose":"857.042, 436.097, 0.950109","left_eye":"874.614, 430.208, 0.88247","right_eye":"856.876, 427.216, 0.795585","left_ear":"910.03, 439.058, 0.880445","right_ear":"0, 0, 0","left_shoulder":"951.149, 518.507, 0.812266","right_shoulder":"856.829, 503.637, 0.86906","left_elbow":"1039.49, 589.139, 0.813105","right_elbow":"839.367, 553.825, 0.75666","left_wrist":"974.748, 574.421, 0.798522","right_wrist":"792.308, 527.348, 0.832975","left_hip":"898.2, 712.755, 0.740648","right_hip":"830.453, 689.28, 0.804713","left_knee":"812.97, 812.831, 0.885493","right_knee":"718.601, 765.851, 0.931448","left_ankle":"833.54, 945.288, 0.775345","right_ankle":"762.673, 901.122, 0.84942","neck":"903.965, 506.834, 0.902414","left_palm":"792.308, 527.348, 0.832975","right_palm":"974.748, 574.421, 0.798522","back":"860, 698.043, 0.816196","waist":"860, 698.043, 0.816196","left_foot":"789.222, 995.316, 0.782894","right_foot":"698.141, 951.036, 0.813939"},"width":1920,"height":1080}}