{"info":{"frame":51,"view":1,"img_key":"C:\\furun\\furun_third\\img\\One-arm_dumbbell_shoulder_press_A_cam1_51.png","name":"One-arm_dumbbell_shoulder_press","standing":0,"pose":12,"grip":1,"e_point":"Shoulder","index":51,"conditions":"A","desc":"Stand with your feet shoulder width holding a handle with an over-grip.","bones":{"nose":"0, 0, 0","left_eye":"0, 0, 0","right_eye":"0, 0, 0","left_ear":"953.993, 342.032, 0.980688","right_ear":"1007.08, 341.97, 0.42482","left_shoulder":"951.152, 409.673, 0.922506","right_shoulder":"1036.52, 406.614, 0.817308","left_elbow":"859.95, 415.548, 0.798376","right_elbow":"1080.64, 477.21, 0.853444","left_wrist":"860.04, 341.87, 0.747838","right_wrist":"1045.25, 530.422, 0.900326","left_hip":"957.032, 592.106, 0.707745","right_hip":"1018.9, 586.204, 0.71264","left_knee":"951.071, 718.675, 0.878588","right_knee":"1010.01, 715.56, 0.817346","left_ankle":"951.075, 839.319, 0.844498","right_ankle":"1007.12, 827.533, 0.757809","neck":"995.29, 409.539, 0.892094","left_palm":"1045.25, 530.422, 0.900326","right_palm":"860.04, 341.87, 0.747838","back":"989.386, 589.152, 0.703753","waist":"989.386, 589.152, 0.703753","left_foot":"907.015, 839.429, 0.620068","right_foot":"977.695, 821.651, 0.395286"},"width":1920,"height":1080}}