{"info":{"frame":40,"view":2,"img_key":"C:\\furun\\furun_third\\img\\One-arm_dumbbell_shoulder_press_A_cam2_40.png","name":"One-arm_dumbbell_shoulder_press","standing":0,"pose":12,"grip":1,"e_point":"Shoulder","index":40,"conditions":"A","desc":"Stand with your feet shoulder width holding a handle with an over-grip.","bones":{"nose":"0, 0, 0","left_eye":"0, 0, 0","right_eye":"0, 0, 0","left_ear":"1069.01, 359.609, 0.501051","right_ear":"1115.88, 386.157, 0.869062","left_shoulder":"1024.8, 386.011, 0.837428","right_shoulder":"1089.39, 456.549, 0.817602","left_elbow":"1039.45, 297.823, 0.791771","right_elbow":"1092.44, 550.769, 0.820509","left_wrist":"1060.02, 224.144, 0.825451","right_wrist":"1071.86, 565.589, 0.233049","left_hip":"998.199, 571.522, 0.737345","right_hip":"1048.41, 586.184, 0.745441","left_knee":"998.351, 692.021, 0.850791","right_knee":"1054.15, 703.897, 0.786723","left_ankle":"998.298, 789.442, 0.802432","right_ankle":"1068.73, 818.788, 0.789902","neck":"1051.24, 415.526, 0.877677","left_palm":"1071.86, 565.589, 0.233049","right_palm":"1060.02, 224.144, 0.825451","back":"1024.64, 577.409, 0.800709","waist":"1024.64, 577.409, 0.800709","left_foot":"1027.75, 795.211, 0.372409","right_foot":"1116.03, 830.394, 0.510449"},"width":1920,"height":1080}}