{"info":{"frame":57,"view":5,"img_key":"C:\\furun\\furun_third\\img\\Side_crunch_B_cam5_57.png","name":"Side_crunch","standing":3,"pose":8,"grip":1,"e_point":"Ab","index":57,"conditions":"B","desc":"Place a handle on your opposite thigh with your arm straight.","bones":{"nose":"1154.21, 692.185, 0.716354","left_eye":"1160.12, 706.904, 0.643174","right_eye":"1163.03, 695.179, 0.405488","left_ear":"1136.63, 739.341, 0.748027","right_ear":"1163.09, 692.07, 0.211329","left_shoulder":"1068.92, 727.536, 0.707708","right_shoulder":"1121.96, 671.523, 0.502634","left_elbow":"974.704, 739.38, 0.817547","right_elbow":"0, 0, 0","left_wrist":"918.835, 689.194, 0.383193","right_wrist":"0, 0, 0","left_hip":"933.477, 671.531, 0.596924","right_hip":"977.722, 627.432, 0.624678","left_knee":"851.149, 542.043, 0.83148","right_knee":"930.563, 518.461, 0.887906","left_ankle":"836.308, 633.345, 0.825833","right_ankle":"892.333, 621.574, 0.509963","neck":"1098.31, 703.965, 0.729287","left_palm":"0, 0, 0","right_palm":"918.835, 689.194, 0.383193","back":"954.153, 648.123, 0.62162","waist":"954.153, 648.123, 0.62162","left_foot":"798.121, 630.352, 0.760236","right_foot":"0, 0, 0"},"width":1920,"height":1080}}