{"info":{"frame":45,"view":1,"img_key":"C:\\furun\\furun_third\\img\\Shoulder_press_A_cam1_45.png","name":"Shoulder_press","standing":0,"pose":12,"grip":1,"e_point":"Waist, Hip","index":45,"conditions":"A","desc":"Stand with your feet shoulder width holding the bar with an over-grip  your hands should be wider than shoulder width.","bones":{"nose":"0, 0, 0","left_eye":"0, 0, 0","right_eye":"0, 0, 0","left_ear":"974.825, 294.857, 0.959406","right_ear":"1027.71, 309.554, 0.397419","left_shoulder":"936.452, 362.491, 0.849436","right_shoulder":"1039.49, 362.363, 0.842092","left_elbow":"856.806, 385.913, 0.856867","right_elbow":"1069.03, 341.84, 0.909511","left_wrist":"856.826, 297.748, 0.842804","right_wrist":"1051.34, 288.971, 0.868701","left_hip":"951.143, 547.929, 0.749504","right_hip":"1010.09, 542.057, 0.691967","left_knee":"948.121, 677.515, 0.795674","right_knee":"1013.01, 668.711, 0.823596","left_ankle":"936.492, 806.98, 0.835515","right_ankle":"1018.87, 783.439, 0.800414","neck":"986.543, 362.48, 0.868668","left_palm":"1051.34, 288.971, 0.868701","right_palm":"856.826, 297.748, 0.842804","back":"977.739, 547.848, 0.776528","waist":"977.739, 547.848, 0.776528","left_foot":"892.32, 809.87, 0.671977","right_foot":"980.646, 786.213, 0.42399"},"width":1920,"height":1080}}