{"info":{"frame":45,"view":4,"img_key":"C:\\furun\\furun_second\\img\\Back_lunge_A_cam4_45.png","name":"Back_lunge","standing":0,"pose":1,"grip":1,"e_point":"Hip, Leg","index":45,"conditions":"A","desc":"Stand with your feet shoulder width and place the bar (with tension) on your upper traps behind the neck.","bones":{"nose":"654.832, 368.907, 0.842054","left_eye":"662.686, 366.74, 0.893494","right_eye":"650.929, 364.897, 0.300348","left_ear":"690.138, 353.21, 0.883486","right_ear":"0, 0, 0","left_shoulder":"737.148, 380.529, 0.80985","right_shoulder":"668.579, 384.432, 0.802207","left_elbow":"786.066, 415.846, 0.914264","right_elbow":"650.985, 388.447, 0.791266","left_wrist":"774.39, 384.508, 0.952161","right_wrist":"635.332, 366.867, 0.825505","left_hip":"748.864, 476.526, 0.81019","right_hip":"709.696, 478.556, 0.824343","left_knee":"715.655, 547.079, 0.806725","right_knee":"725.325, 541.149, 0.775209","left_ankle":"725.326, 621.549, 0.819786","right_ankle":"758.658, 554.965, 0.880163","neck":"699.971, 382.519, 0.895646","left_palm":"635.332, 366.867, 0.825505","right_palm":"774.39, 384.508, 0.952161","back":"729.236, 476.624, 0.882513","waist":"729.236, 476.624, 0.882513","left_foot":"701.862, 646.959, 0.652335","right_foot":"756.732, 588.292, 0.808237"},"width":1920,"height":1080}}