{"info":{"frame":50,"view":1,"img_key":"C:\\furun\\furun_third\\img\\Seated_fly_B_cam1_50.png","name":"Seated_fly","standing":2,"pose":13,"grip":1,"e_point":"Chest","index":50,"conditions":"B","desc":"Place the handles at the lower-chest level at your side while keeping your torso upright and arms slightly bent.","bones":{"nose":"833.655, 436.142, 0.0849587","left_eye":"836.246, 439.111, 0.100784","right_eye":"0, 0, 0","left_ear":"853.986, 453.812, 0.923099","right_ear":"901.165, 453.634, 0.234607","left_shoulder":"845.254, 521.45, 0.812391","right_shoulder":"927.751, 506.698, 0.951508","left_elbow":"786.393, 577.382, 0.951404","right_elbow":"983.544, 550.78, 0.872232","left_wrist":"698.075, 598.067, 0.870718","right_wrist":"1045.34, 553.82, 0.933182","left_hip":"859.994, 668.575, 0.761199","right_hip":"915.915, 671.492, 0.804075","left_knee":"768.689, 668.508, 0.872917","right_knee":"860.013, 665.657, 0.602856","left_ankle":"798.124, 777.54, 0.810305","right_ankle":"859.915, 771.65, 0.857384","neck":"883.542, 509.677, 0.913791","left_palm":"1045.34, 553.82, 0.933182","right_palm":"698.075, 598.067, 0.870718","back":"886.513, 668.667, 0.843599","waist":"886.513, 668.667, 0.843599","left_foot":"762.785, 768.743, 0.75114","right_foot":"856.98, 765.865, 0.262294"},"width":1920,"height":1080}}