{"info":{"frame":1,"view":1,"img_key":"C:\\furun\\furun_third\\img\\Seated_fly_B_cam1_01.png","name":"Seated_fly","standing":2,"pose":13,"grip":1,"e_point":"Chest","index":1,"conditions":"B","desc":"Place the handles at the lower-chest level at your side while keeping your torso upright and arms slightly bent.","bones":{"nose":"0, 0, 0","left_eye":"0, 0, 0","right_eye":"0, 0, 0","left_ear":"848.103, 453.708, 0.895957","right_ear":"898.132, 447.847, 0.458152","left_shoulder":"833.497, 521.395, 0.884984","right_shoulder":"927.603, 506.755, 0.938808","left_elbow":"806.996, 600.866, 0.913372","right_elbow":"971.82, 574.513, 0.932663","left_wrist":"759.774, 671.71, 0.828297","right_wrist":"1021.92, 624.409, 0.928912","left_hip":"856.899, 668.594, 0.785608","right_hip":"912.955, 671.479, 0.797524","left_knee":"774.535, 671.639, 0.811231","right_knee":"854.039, 665.642, 0.506676","left_ankle":"809.895, 777.513, 0.793084","right_ankle":"859.917, 768.731, 0.779467","neck":"880.545, 509.766, 0.932001","left_palm":"1021.92, 624.409, 0.928912","right_palm":"759.774, 671.71, 0.828297","back":"883.564, 668.688, 0.857131","waist":"883.564, 668.688, 0.857131","left_foot":"765.814, 771.636, 0.645304","right_foot":"839.377, 768.663, 0.179414"},"width":1920,"height":1080}}