{"info":{"frame":56,"view":4,"img_key":"C:\\furun\\furun_second\\img\\Back_lunge_B_cam4_56.png","name":"Back_lunge","standing":0,"pose":1,"grip":1,"e_point":"Hip, Leg","index":56,"conditions":"B","desc":"Take a large step backward while maintaining shoulder width  keeping your back arched and?hips level.","bones":{"nose":"647.036, 290.557, 0.924979","left_eye":"652.904, 286.528, 0.916025","right_eye":"643.103, 286.543, 0.827505","left_ear":"680.311, 288.486, 0.961904","right_ear":"0, 0, 0","left_shoulder":"713.58, 335.472, 0.888195","right_shoulder":"647.017, 329.644, 0.840999","left_elbow":"748.877, 382.502, 0.909071","right_elbow":"633.236, 368.794, 0.924949","left_wrist":"747.008, 337.414, 0.884375","right_wrist":"619.504, 321.887, 0.917457","left_hip":"699.883, 449.195, 0.771048","right_hip":"652.944, 449.153, 0.754103","left_knee":"711.646, 537.311, 0.893164","right_knee":"666.653, 533.355, 0.838064","left_ankle":"725.36, 617.695, 0.851939","right_ankle":"672.479, 605.911, 0.81823","neck":"680.287, 333.552, 0.922495","left_palm":"619.504, 321.887, 0.917457","right_palm":"747.008, 337.414, 0.884375","back":"680.229, 449.18, 0.801938","waist":"680.229, 449.18, 0.801938","left_foot":"705.814, 639.185, 0.661346","right_foot":"649.031, 631.343, 0.794069"},"width":1920,"height":1080}}