{"info":{"frame":2,"view":3,"img_key":"C:\\furun\\furun_second\\img\\Dumbbell_bent-over_lateral_raise_KEY_cam3_02.png","name":"Dumbbell_bent-over_lateral_raise","standing":3,"pose":2,"grip":1,"e_point":"Shoulder","index":2,"conditions":"KEY","desc":"Throughout the exercise  the speed and level of both handles should be the same.","bones":{"nose":"645.068, 396.23, 0.868306","left_eye":"652.901, 382.614, 0.952641","right_eye":"633.31, 384.45, 0.951854","left_ear":"666.689, 366.91, 0.724426","right_ear":"617.531, 368.821, 0.860992","left_shoulder":"694.038, 386.504, 0.821439","right_shoulder":"588.276, 396.219, 0.837267","left_elbow":"695.87, 456.992, 0.858094","right_elbow":"590.158, 460.883, 0.89922","left_wrist":"666.679, 511.798, 0.900011","right_wrist":"617.642, 515.788, 0.871728","left_hip":"664.681, 449.191, 0.773878","right_hip":"615.637, 451.075, 0.728932","left_knee":"682.215, 531.426, 0.77887","right_knee":"603.925, 537.33, 0.823751","left_ankle":"680.408, 623.499, 0.839232","right_ankle":"615.643, 631.305, 0.815743","neck":"639.225, 390.34, 0.743814","left_palm":"617.642, 515.788, 0.871728","right_palm":"666.679, 511.798, 0.900011","back":"637.274, 449.188, 0.774371","waist":"637.274, 449.188, 0.774371","left_foot":"682.304, 654.848, 0.767611","right_foot":"605.942, 658.792, 0.642205"},"width":1920,"height":1080}}