{"info":{"frame":6,"view":2,"img_key":"C:\\furun\\furun_third\\img\\Shoulder_press_A_cam2_06.png","name":"Shoulder_press","standing":0,"pose":12,"grip":1,"e_point":"Waist, Hip","index":6,"conditions":"A","desc":"Stand with your feet shoulder width holding the bar with an over-grip  your hands should be wider than shoulder width.","bones":{"nose":"0, 0, 0","left_eye":"0, 0, 0","right_eye":"1092.47, 280.136, 0.206361","left_ear":"1033.6, 303.643, 0.158256","right_ear":"1074.89, 294.82, 0.882998","left_shoulder":"1001.23, 365.452, 0.941789","right_shoulder":"1095.4, 377.259, 0.862124","left_elbow":"989.417, 433.027, 0.806588","right_elbow":"1142.6, 453.672, 0.913836","left_wrist":"998.28, 362.6, 0.307598","right_wrist":"1168.93, 386.098, 0.9032","left_hip":"1021.8, 536.202, 0.746571","right_hip":"1077.72, 545.044, 0.72322","left_knee":"1010.04, 659.821, 0.778471","right_knee":"1074.8, 671.497, 0.850675","left_ankle":"1001.22, 765.75, 0.853683","right_ankle":"1071.96, 786.444, 0.871804","neck":"1048.36, 368.501, 0.901214","left_palm":"1168.93, 386.098, 0.9032","right_palm":"998.28, 362.6, 0.307598","back":"1048.32, 542.05, 0.771367","waist":"1048.32, 542.05, 0.771367","left_foot":"0, 0, 0","right_foot":"1116.04, 792.334, 0.57479"},"width":1920,"height":1080}}