{"info":{"frame":44,"view":4,"img_key":"C:\\furun\\furun_second\\img\\Dumbbell_bent-over_lateral_raise_B_cam4_44.png","name":"Dumbbell_bent-over_lateral_raise","standing":3,"pose":2,"grip":1,"e_point":"Shoulder","index":44,"conditions":"B","desc":"Bend your knees slightly and lean forward while keeping your back arched.","bones":{"nose":"617.519, 411.876, 0.882678","left_eye":"619.497, 400.266, 0.914392","right_eye":"613.665, 402.128, 0.111639","left_ear":"646.966, 386.504, 0.868186","right_ear":"0, 0, 0","left_shoulder":"694.005, 400.105, 0.820524","right_shoulder":"625.458, 402.137, 0.755086","left_elbow":"731.309, 447.217, 0.894495","right_elbow":"617.566, 443.216, 0.926827","left_wrist":"737.11, 511.828, 0.837478","right_wrist":"590.262, 490.213, 0.829422","left_hip":"729.389, 456.952, 0.778668","right_hip":"682.383, 460.801, 0.823737","left_knee":"727.372, 533.403, 0.851636","right_knee":"672.477, 527.557, 0.791811","left_ankle":"727.422, 619.588, 0.863343","right_ankle":"680.282, 603.982, 0.879925","neck":"658.769, 400.142, 0.843122","left_palm":"590.262, 490.213, 0.829422","right_palm":"737.11, 511.828, 0.837478","back":"709.724, 458.875, 0.814095","waist":"709.724, 458.875, 0.814095","left_foot":"703.838, 637.281, 0.642923","right_foot":"652.955, 631.318, 0.784967"},"width":1920,"height":1080}}