{"info":{"frame":26,"view":4,"img_key":"C:\\furun\\furun_second\\img\\Dumbbell_bent-over_lateral_raise_B_cam4_26.png","name":"Dumbbell_bent-over_lateral_raise","standing":3,"pose":2,"grip":1,"e_point":"Shoulder","index":26,"conditions":"B","desc":"Bend your knees slightly and lean forward while keeping your back arched.","bones":{"nose":"635.225, 443.283, 0.771968","left_eye":"635.273, 433.541, 0.724052","right_eye":"629.404, 435.437, 0.111842","left_ear":"648.888, 415.833, 0.794101","right_ear":"0, 0, 0","left_shoulder":"696.039, 400.109, 0.769764","right_shoulder":"629.335, 398.223, 0.750842","left_elbow":"748.919, 390.365, 0.808301","right_elbow":"598.012, 382.612, 0.88337","left_wrist":"790.106, 400.255, 0.90568","right_wrist":"551.02, 384.421, 0.882008","left_hip":"733.209, 449.177, 0.77938","right_hip":"686.224, 453.06, 0.779544","left_knee":"727.276, 529.458, 0.853621","right_knee":"674.45, 525.511, 0.841681","left_ankle":"729.219, 617.682, 0.817837","right_ankle":"680.295, 603.929, 0.885028","neck":"660.726, 400.189, 0.841183","left_palm":"551.02, 384.421, 0.882008","right_palm":"790.106, 400.255, 0.90568","back":"711.666, 451.121, 0.849506","waist":"711.666, 451.121, 0.849506","left_foot":"701.881, 641.118, 0.616664","right_foot":"654.838, 631.332, 0.799755"},"width":1920,"height":1080}}