{"info":{"frame":29,"view":5,"img_key":"C:\\furun\\furun_second\\img\\Dumbbell_bent-over_lateral_raise_KEY_cam5_29.png","name":"Dumbbell_bent-over_lateral_raise","standing":3,"pose":2,"grip":1,"e_point":"Shoulder","index":29,"conditions":"KEY","desc":"Throughout the exercise  the speed and level of both handles should be the same.","bones":{"nose":"695.925, 402.138, 0.855149","left_eye":"0, 0, 0","right_eye":"692.057, 398.164, 0.857517","left_ear":"0, 0, 0","right_ear":"666.578, 382.583, 0.944326","left_shoulder":"678.289, 366.824, 0.73748","right_shoulder":"619.511, 388.397, 0.741732","left_elbow":"699.946, 347.225, 0.833789","right_elbow":"560.811, 396.163, 0.857145","left_wrist":"739.102, 335.571, 0.876773","right_wrist":"523.517, 406.051, 0.823657","left_hip":"607.825, 441.284, 0.712384","right_hip":"562.798, 445.279, 0.796365","left_knee":"633.299, 509.796, 0.92326","right_knee":"584.333, 521.619, 0.844919","left_ankle":"633.32, 590.179, 0.864314","right_ankle":"586.319, 607.816, 0.826507","neck":"646.951, 382.435, 0.829499","left_palm":"523.517, 406.051, 0.823657","right_palm":"739.102, 335.571, 0.876773","back":"586.328, 445.153, 0.824553","waist":"586.328, 445.153, 0.824553","left_foot":"664.551, 611.776, 0.738558","right_foot":"611.715, 635.214, 0.743614"},"width":1920,"height":1080}}