{"info":{"frame":42,"view":5,"img_key":"C:\\furun\\furun_third\\img\\Side_crunch_KEY_cam5_42.png","name":"Side_crunch","standing":3,"pose":8,"grip":1,"e_point":"Ab","index":42,"conditions":"KEY","desc":"Throughout the exercise  keep your lower back pressed against the bench.","bones":{"nose":"1101.26, 621.48, 0.528294","left_eye":"1113.05, 624.457, 0.560685","right_eye":"0, 0, 0","left_ear":"1104.24, 662.664, 0.772078","right_ear":"0, 0, 0","left_shoulder":"1048.21, 695.007, 0.73543","right_shoulder":"1107.13, 671.495, 0.427993","left_elbow":"965.881, 653.928, 0.61724","right_elbow":"1027.69, 642.109, 0.187107","left_wrist":"924.649, 597.847, 0.819323","right_wrist":"1021.74, 627.444, 0.0612917","left_hip":"924.682, 671.657, 0.673388","right_hip":"992.322, 624.528, 0.614948","left_knee":"848.184, 530.307, 0.87174","right_knee":"927.546, 509.706, 0.879084","left_ankle":"836.367, 636.276, 0.8372","right_ankle":"877.514, 621.464, 0.557783","neck":"1071.97, 680.446, 0.729206","left_palm":"1021.74, 627.444, 0.0612917","right_palm":"924.649, 597.847, 0.819323","back":"948.244, 659.801, 0.492589","waist":"948.244, 659.801, 0.492589","left_foot":"798.168, 636.214, 0.757915","right_foot":"0, 0, 0"},"width":1920,"height":1080}}