{"info":{"frame":45,"view":1,"img_key":"C:\\furun\\furun_third\\img\\Shoulder_press_C_cam1_45.png","name":"Shoulder_press","standing":0,"pose":12,"grip":1,"e_point":"Waist, Hip","index":45,"conditions":"C","desc":"Push the bar vertically by extending your elbows until the bar is above your head.","bones":{"nose":"0, 0, 0","left_eye":"0, 0, 0","right_eye":"0, 0, 0","left_ear":"977.772, 291.974, 0.9392","right_ear":"1039.47, 297.835, 0.319576","left_shoulder":"951.209, 362.53, 0.865729","right_shoulder":"1051.2, 359.586, 0.843356","left_elbow":"860.096, 389.132, 0.890448","right_elbow":"1080.7, 362.626, 0.827689","left_wrist":"856.979, 315.378, 0.884318","right_wrist":"1057.15, 297.798, 0.76125","left_hip":"957.154, 550.854, 0.726417","right_hip":"1024.62, 550.836, 0.750291","left_knee":"948.107, 677.478, 0.803668","right_knee":"1015.91, 671.455, 0.830206","left_ankle":"936.418, 806.934, 0.837614","right_ankle":"1018.89, 783.342, 0.805645","neck":"1001.17, 362.495, 0.919452","left_palm":"1057.15, 297.798, 0.76125","right_palm":"856.979, 315.378, 0.884318","back":"995.303, 550.833, 0.769513","waist":"995.303, 550.833, 0.769513","left_foot":"892.335, 809.791, 0.690842","right_foot":"977.728, 786.247, 0.495888"},"width":1920,"height":1080}}