{"info":{"frame":15,"view":1,"img_key":"C:\\furun\\furun_third\\img\\Shoulder_press_C_cam1_15.png","name":"Shoulder_press","standing":0,"pose":12,"grip":1,"e_point":"Waist, Hip","index":15,"conditions":"C","desc":"Push the bar vertically by extending your elbows until the bar is above your head.","bones":{"nose":"0, 0, 0","left_eye":"951.121, 280.067, 0.0729609","right_eye":"0, 0, 0","left_ear":"957.181, 291.959, 0.926517","right_ear":"1010.03, 297.805, 0.283202","left_shoulder":"933.46, 365.437, 0.871161","right_shoulder":"1042.42, 362.459, 0.828716","left_elbow":"853.923, 406.605, 0.85035","right_elbow":"1048.17, 341.875, 0.704678","left_wrist":"836.407, 321.429, 0.818004","right_wrist":"1027.75, 306.647, 0.724651","left_hip":"962.98, 553.76, 0.718402","right_hip":"1024.62, 550.937, 0.743937","left_knee":"948.195, 683.322, 0.816667","right_knee":"1018.81, 671.582, 0.843296","left_ankle":"936.481, 806.927, 0.835196","right_ankle":"1018.74, 783.452, 0.809581","neck":"989.395, 362.625, 0.867532","left_palm":"1027.75, 306.647, 0.724651","right_palm":"836.407, 321.429, 0.818004","back":"998.083, 550.963, 0.777362","waist":"998.083, 550.963, 0.777362","left_foot":"892.307, 809.87, 0.711327","right_foot":"977.72, 786.219, 0.438602"},"width":1920,"height":1080}}