{"info":{"frame":53,"view":1,"img_key":"C:\\furun\\furun_second\\img\\Dumbbell_bent-over_lateral_raise_E_cam1_53.png","name":"Dumbbell_bent-over_lateral_raise","standing":3,"pose":2,"grip":1,"e_point":"Shoulder","index":53,"conditions":"E","desc":"Lower the handles back to the starting position in a controlled manner.","bones":{"nose":"576.526, 333.584, 0.0862015","left_eye":"574.617, 325.677, 0.197141","right_eye":"0, 0, 0","left_ear":"586.242, 323.797, 0.870792","right_ear":"605.963, 317.906, 0.168642","left_shoulder":"588.317, 349.156, 0.880197","right_shoulder":"645.038, 329.635, 0.778402","left_elbow":"604.031, 409.984, 0.894955","right_elbow":"656.844, 380.573, 0.0732362","left_wrist":"617.538, 453.028, 0.854245","right_wrist":"0, 0, 0","left_hip":"670.501, 413.838, 0.729919","right_hip":"711.624, 404.081, 0.743813","left_knee":"629.391, 482.443, 0.819297","right_knee":"682.219, 478.488, 0.892352","left_ankle":"625.488, 558.91, 0.799175","right_ankle":"678.302, 545.122, 0.764134","neck":"617.653, 337.4, 0.965934","left_palm":"0, 0, 0","right_palm":"617.538, 453.028, 0.854245","back":"692.051, 409.934, 0.729892","waist":"692.051, 409.934, 0.729892","left_foot":"599.963, 560.787, 0.667843","right_foot":"650.94, 549.054, 0.444969"},"width":1920,"height":1080}}