{"info":{"frame":36,"view":3,"img_key":"C:\\furun\\furun_second\\img\\Dumbbell_bent-over_lateral_raise_D_cam3_36.png","name":"Dumbbell_bent-over_lateral_raise","standing":3,"pose":2,"grip":1,"e_point":"Shoulder","index":36,"conditions":"D","desc":"Lift the handles laterally to the ceiling until shoulder level by raising your arms while keeping your elbows locked.","bones":{"nose":"637.184, 398.236, 0.854407","left_eye":"648.879, 386.517, 0.865599","right_eye":"625.49, 388.412, 0.762933","left_ear":"662.662, 366.869, 0.647603","right_ear":"609.816, 372.704, 0.446149","left_shoulder":"692.029, 362.898, 0.756155","right_shoulder":"588.224, 368.773, 0.838299","left_elbow":"746.967, 353.218, 0.865213","right_elbow":"533.357, 366.871, 0.816421","left_wrist":"809.63, 337.56, 0.848545","right_wrist":"466.761, 357.092, 0.810536","left_hip":"668.562, 447.189, 0.780575","right_hip":"605.932, 449.121, 0.757636","left_knee":"682.202, 537.228, 0.831613","right_knee":"603.913, 539.307, 0.866536","left_ankle":"680.21, 621.578, 0.816316","right_ankle":"615.624, 631.368, 0.830402","neck":"637.235, 368.757, 0.912267","left_palm":"466.761, 357.092, 0.810536","right_palm":"809.63, 337.56, 0.848545","back":"637.269, 447.26, 0.800658","waist":"637.269, 447.26, 0.800658","left_foot":"682.346, 652.886, 0.776606","right_foot":"605.924, 662.662, 0.786799"},"width":1920,"height":1080}}