{"info":{"frame":22,"view":4,"img_key":"C:\\furun\\furun_second\\img\\Dumbbell_bent-over_lateral_raise_KEY_cam4_22.png","name":"Dumbbell_bent-over_lateral_raise","standing":3,"pose":2,"grip":1,"e_point":"Shoulder","index":22,"conditions":"KEY","desc":"Throughout the exercise  the speed and level of both handles should be the same.","bones":{"nose":"615.657, 425.646, 0.859536","left_eye":"619.521, 415.904, 0.935456","right_eye":"605.916, 415.848, 0.11121","left_ear":"646.996, 402.156, 0.864835","right_ear":"0, 0, 0","left_shoulder":"694.062, 415.768, 0.808622","right_shoulder":"631.347, 413.834, 0.768593","left_elbow":"742.925, 458.957, 0.884392","right_elbow":"603.945, 443.254, 0.908658","left_wrist":"750.849, 515.774, 0.825642","right_wrist":"572.644, 482.425, 0.857971","left_hip":"731.303, 458.942, 0.793175","right_hip":"688.13, 460.924, 0.808038","left_knee":"727.326, 533.411, 0.826414","right_knee":"676.38, 525.5, 0.835367","left_ankle":"727.365, 619.593, 0.864062","right_ankle":"680.288, 603.918, 0.890058","neck":"662.613, 413.881, 0.847837","left_palm":"572.644, 482.425, 0.857971","right_palm":"750.849, 515.774, 0.825642","back":"711.685, 460.817, 0.862362","waist":"711.685, 460.817, 0.862362","left_foot":"703.805, 639.167, 0.68342","right_foot":"654.841, 631.32, 0.796647"},"width":1920,"height":1080}}