{"info":{"frame":26,"view":3,"img_key":"C:\\furun\\furun_third\\img\\Side_crunch_B_cam3_26.png","name":"Side_crunch","standing":3,"pose":8,"grip":1,"e_point":"Ab","index":26,"conditions":"B","desc":"Place a handle on your opposite thigh with your arm straight.","bones":{"nose":"0, 0, 0","left_eye":"1048.27, 356.67, 0.0767765","right_eye":"0, 0, 0","left_ear":"1048.46, 386.121, 0.855714","right_ear":"1116.04, 433.081, 0.43422","left_shoulder":"980.595, 433.033, 0.806723","right_shoulder":"1118.97, 489.063, 0.776954","left_elbow":"1001.09, 341.799, 0.87213","right_elbow":"1186.52, 527.375, 0.89017","left_wrist":"1039.4, 291.846, 0.743978","right_wrist":"1118.98, 450.771, 0.531332","left_hip":"968.856, 609.763, 0.568456","right_hip":"1048.32, 630.316, 0.576101","left_knee":"0, 0, 0","right_knee":"1074.74, 624.376, 0.111929","left_ankle":"0, 0, 0","right_ankle":"1015.89, 742.184, 0.112126","neck":"1048.46, 459.583, 0.869195","left_palm":"1118.98, 450.771, 0.531332","right_palm":"1039.4, 291.846, 0.743978","back":"1004.23, 621.505, 0.649942","waist":"1004.23, 621.505, 0.649942","left_foot":"0, 0, 0","right_foot":"1015.89, 768.676, 0.0805192"},"width":1920,"height":1080}}