{"info":{"frame":27,"view":2,"img_key":"C:\\furun\\furun_second\\img\\High-pull_KEY_cam2_27.png","name":"High-pull","standing":0,"pose":2,"grip":1,"e_point":"Back","index":27,"conditions":"KEY","desc":"Throughout the exercise  the speed and level of both handles should be the same.","bones":{"nose":"0, 0, 0","left_eye":"0, 0, 0","right_eye":"727.277, 221.905, 0.0741346","left_ear":"682.277, 225.741, 0.466242","right_ear":"715.617, 227.676, 0.858878","left_shoulder":"664.639, 257.211, 0.885918","right_shoulder":"727.268, 259.027, 0.827875","left_elbow":"635.361, 214.023, 0.877745","right_elbow":"764.607, 229.721, 0.797326","left_wrist":"680.266, 219.939, 0.78761","right_wrist":"746.915, 237.505, 0.204263","left_hip":"676.421, 380.579, 0.704012","right_hip":"713.627, 382.534, 0.749515","left_knee":"670.568, 460.851, 0.797988","right_knee":"711.628, 466.795, 0.821859","left_ankle":"666.691, 539.315, 0.777719","right_ankle":"709.646, 549.063, 0.75382","neck":"695.987, 259.055, 0.921322","left_palm":"746.915, 237.505, 0.204263","right_palm":"680.266, 219.939, 0.78761","back":"695.974, 382.466, 0.779933","waist":"695.974, 382.466, 0.779933","left_foot":"693.946, 539.267, 0.161761","right_foot":"731.267, 554.871, 0.693135"},"width":1920,"height":1080}}