{"info":{"frame":34,"view":1,"img_key":"C:\\furun\\furun_second\\img\\Arnold_press_E_cam1_34.png","name":"Arnold_press","standing":0,"pose":12,"grip":1,"e_point":"Shoulder","index":34,"conditions":"E","desc":"Lower the handles back to the starting position in a controlled manner.","bones":{"nose":"666.614, 257.051, 0.383843","left_eye":"676.362, 253.188, 0.279718","right_eye":"0, 0, 0","left_ear":"666.656, 261.129, 0.66096","right_ear":"0, 0, 0","left_shoulder":"633.366, 286.532, 0.82004","right_shoulder":"684.258, 302.147, 0.778279","left_elbow":"629.411, 225.746, 0.797399","right_elbow":"695.885, 225.783, 0.701423","left_wrist":"633.306, 165.101, 0.859789","right_wrist":"686.192, 167.009, 0.815622","left_hip":"617.573, 394.285, 0.720089","right_hip":"650.977, 392.324, 0.729142","left_knee":"617.625, 476.542, 0.865338","right_knee":"658.8, 468.762, 0.781958","left_ankle":"633.28, 556.903, 0.870245","right_ankle":"674.439, 545.129, 0.767347","neck":"662.718, 290.406, 0.903237","left_palm":"686.192, 167.009, 0.815622","right_palm":"633.306, 165.101, 0.859789","back":"633.38, 394.263, 0.772743","waist":"633.38, 394.263, 0.772743","left_foot":"603.95, 558.906, 0.517311","right_foot":"654.869, 543.171, 0.32376"},"width":1920,"height":1080}}