{"info":{"frame":15,"view":2,"img_key":"C:\\furun\\furun_second\\img\\Dumbbell_bent-over_lateral_raise_A_cam2_15.png","name":"Dumbbell_bent-over_lateral_raise","standing":3,"pose":2,"grip":1,"e_point":"Shoulder","index":15,"conditions":"A","desc":"Stand with your feet shoulder width holding the opposite handles with a neutral-grip.","bones":{"nose":"772.324, 315.935, 0.0789254","left_eye":"0, 0, 0","right_eye":"772.436, 308.061, 0.178751","left_ear":"741.02, 294.421, 0.246714","right_ear":"762.577, 306.192, 0.898128","left_shoulder":"699.897, 317.876, 0.844488","right_shoulder":"758.669, 337.425, 0.906385","left_elbow":"666.655, 357.078, 0.307684","right_elbow":"745.015, 400.074, 0.946877","left_wrist":"0, 0, 0","right_wrist":"727.396, 435.439, 0.859319","left_hip":"648.894, 394.257, 0.751471","right_hip":"684.226, 400.208, 0.764454","left_knee":"666.554, 462.849, 0.871998","right_knee":"711.73, 472.661, 0.858745","left_ankle":"666.538, 537.337, 0.789002","right_ankle":"709.714, 550.974, 0.783684","neck":"729.29, 323.811, 0.889509","left_palm":"727.396, 435.439, 0.859319","right_palm":"0, 0, 0","back":"666.555, 398.167, 0.803864","waist":"666.555, 398.167, 0.803864","left_foot":"692.022, 539.268, 0.349081","right_foot":"733.245, 554.912, 0.612687"},"width":1920,"height":1080}}