{"info":{"frame":40,"view":1,"img_key":"C:\\furun\\furun_second\\img\\High-pull_KEY_cam1_40.png","name":"High-pull","standing":0,"pose":2,"grip":1,"e_point":"Back","index":40,"conditions":"KEY","desc":"Throughout the exercise  the speed and level of both handles should be the same.","bones":{"nose":"0, 0, 0","left_eye":"0, 0, 0","right_eye":"0, 0, 0","left_ear":"633.35, 227.703, 0.994539","right_ear":"670.49, 225.85, 0.549377","left_shoulder":"627.422, 268.917, 0.795951","right_shoulder":"682.381, 261.107, 0.844227","left_elbow":"582.377, 257.118, 0.844134","right_elbow":"717.537, 227.808, 0.868665","left_wrist":"0, 0, 0","right_wrist":"676.367, 229.694, 0.788315","left_hip":"633.196, 384.561, 0.725592","right_hip":"668.551, 384.497, 0.731972","left_knee":"631.35, 478.477, 0.845737","right_knee":"666.706, 470.717, 0.822029","left_ankle":"633.307, 560.856, 0.825957","right_ankle":"676.421, 553.007, 0.762329","neck":"654.832, 266.931, 0.834152","left_palm":"676.367, 229.694, 0.788315","right_palm":"0, 0, 0","back":"650.868, 384.522, 0.783626","waist":"650.868, 384.522, 0.783626","left_foot":"600.01, 564.694, 0.635114","right_foot":"649.041, 551.014, 0.428017"},"width":1920,"height":1080}}