{"info":{"frame":27,"view":2,"img_key":"C:\\furun\\furun_third\\img\\Seated_shoulder_press_KEY_cam2_27.png","name":"Seated_shoulder_press","standing":2,"pose":12,"grip":1,"e_point":"Shoulder","index":27,"conditions":"KEY","desc":"Throughout the exercise  keep your forearms vertical to the ground.","bones":{"nose":"0, 0, 0","left_eye":"0, 0, 0","right_eye":"1192.54, 412.528, 0.0806841","left_ear":"1142.58, 427.32, 0.24961","right_ear":"1189.55, 433.016, 0.933426","left_shoulder":"1124.9, 468.469, 0.806629","right_shoulder":"1210.26, 480.294, 0.865171","left_elbow":"1115.93, 397.853, 0.837318","right_elbow":"1248.48, 412.638, 0.833098","left_wrist":"1098.44, 338.852, 0.841417","right_wrist":"1274.86, 344.967, 0.823428","left_hip":"1139.5, 627.448, 0.789319","right_hip":"1189.65, 630.401, 0.748522","left_knee":"1169.05, 642.111, 0.290466","right_knee":"1266.08, 644.964, 0.851857","left_ankle":"1166.13, 709.815, 0.275032","right_ankle":"1251.3, 745.211, 0.774408","neck":"1166.1, 477.275, 0.90141","left_palm":"1274.86, 344.967, 0.823428","right_palm":"1098.44, 338.852, 0.841417","back":"1163.2, 627.503, 0.804496","waist":"1163.2, 627.503, 0.804496","left_foot":"0, 0, 0","right_foot":"1280.87, 762.777, 0.444431"},"width":1920,"height":1080}}