{"info":{"frame":24,"view":4,"img_key":"C:\\furun\\furun_third\\img\\One-arm_dumbbell_shoulder_press_A_cam4_24.png","name":"One-arm_dumbbell_shoulder_press","standing":0,"pose":12,"grip":1,"e_point":"Shoulder","index":24,"conditions":"A","desc":"Stand with your feet shoulder width holding a handle with an over-grip.","bones":{"nose":"998.311, 415.568, 0.933481","left_eye":"1015.88, 409.732, 0.926022","right_eye":"998.136, 409.597, 0.921127","left_ear":"1048.23, 424.337, 0.898435","right_ear":"0, 0, 0","left_shoulder":"1077.75, 483.292, 0.853782","right_shoulder":"977.775, 492.062, 0.867394","left_elbow":"1136.65, 459.687, 0.909759","right_elbow":"962.897, 553.871, 0.869559","left_wrist":"1113.07, 385.966, 0.903709","right_wrist":"971.696, 621.638, 0.894771","left_hip":"1062.99, 674.524, 0.746315","right_hip":"995.345, 674.525, 0.770339","left_knee":"1071.91, 809.776, 0.88222","right_knee":"1007.15, 801.118, 0.805573","left_ankle":"1086.49, 930.601, 0.828375","right_ankle":"1021.66, 907.108, 0.876511","neck":"1027.74, 486.191, 0.882016","left_palm":"971.696, 621.638, 0.894771","right_palm":"1113.07, 385.966, 0.903709","back":"1024.81, 674.539, 0.798102","waist":"1024.81, 674.539, 0.798102","left_foot":"1045.45, 965.876, 0.757901","right_foot":"977.562, 945.301, 0.761528"},"width":1920,"height":1080}}