{"info":{"frame":55,"view":2,"img_key":"C:\\furun\\furun_third\\img\\Seated_fly_B_cam2_55.png","name":"Seated_fly","standing":2,"pose":13,"grip":1,"e_point":"Chest","index":55,"conditions":"B","desc":"Place the handles at the lower-chest level at your side while keeping your torso upright and arms slightly bent.","bones":{"nose":"0, 0, 0","left_eye":"0, 0, 0","right_eye":"1183.73, 436.195, 0.235827","left_ear":"1119.04, 442.037, 0.295136","right_ear":"1166.05, 444.97, 0.884785","left_shoulder":"1092.31, 503.704, 0.884173","right_shoulder":"1165.95, 506.785, 0.898989","left_elbow":"1030.68, 545.032, 0.809501","right_elbow":"1210.1, 577.247, 0.916134","left_wrist":"971.73, 553.916, 0.876587","right_wrist":"1248.42, 624.43, 0.880222","left_hip":"1095.4, 659.816, 0.749646","right_hip":"1148.41, 662.71, 0.755287","left_knee":"1160.07, 662.763, 0.345701","right_knee":"1236.73, 653.88, 0.789361","left_ankle":"1148.41, 753.986, 0.60869","right_ankle":"1210.12, 762.738, 0.856728","neck":"1124.85, 503.928, 0.900952","left_palm":"1248.42, 624.43, 0.880222","right_palm":"971.73, 553.916, 0.876587","back":"1121.83, 662.72, 0.784813","waist":"1121.83, 662.72, 0.784813","left_foot":"1168.95, 739.309, 0.1368","right_foot":"1242.53, 765.76, 0.782669"},"width":1920,"height":1080}}