{"info":{"frame":17,"view":4,"img_key":"C:\\furun\\furun_second\\img\\Back_lunge_D_cam4_17.png","name":"Back_lunge","standing":0,"pose":1,"grip":1,"e_point":"Hip, Leg","index":17,"conditions":"D","desc":"Lift the bar by extending your knees and hips while bringing your rear leg forward to the standing position.","bones":{"nose":"664.726, 329.656, 0.91068","left_eye":"674.423, 319.921, 0.894612","right_eye":"662.692, 319.922, 0.857283","left_ear":"698.016, 319.841, 0.951102","right_ear":"0, 0, 0","left_shoulder":"742.917, 355.13, 0.864727","right_shoulder":"664.725, 351.183, 0.897306","left_elbow":"780.222, 404.124, 0.845602","right_elbow":"650.955, 382.566, 0.912609","left_wrist":"776.284, 366.76, 0.924999","right_wrist":"635.366, 349.199, 0.862087","left_hip":"739.044, 470.683, 0.744037","right_hip":"695.968, 468.717, 0.78663","left_knee":"727.336, 547.097, 0.757178","right_knee":"705.802, 552.906, 0.803357","left_ankle":"745.069, 560.826, 0.803619","right_ankle":"725.329, 619.642, 0.783661","neck":"699.982, 353.177, 0.901568","left_palm":"635.366, 349.199, 0.862087","right_palm":"776.284, 366.76, 0.924999","back":"713.699, 468.744, 0.800412","waist":"713.699, 468.744, 0.800412","left_foot":"741.021, 588.245, 0.689532","right_foot":"707.77, 648.948, 0.609504"},"width":1920,"height":1080}}