{"info":{"frame":42,"view":2,"img_key":"C:\\furun\\furun_third\\img\\Shoulder_press_C_cam2_42.png","name":"Shoulder_press","standing":0,"pose":12,"grip":1,"e_point":"Waist, Hip","index":42,"conditions":"C","desc":"Push the bar vertically by extending your elbows until the bar is above your head.","bones":{"nose":"1086.56, 294.799, 0.0808954","left_eye":"0, 0, 0","right_eye":"1083.55, 288.881, 0.215574","left_ear":"1021.83, 294.956, 0.197198","right_ear":"1068.85, 294.919, 0.917725","left_shoulder":"989.432, 359.599, 0.813933","right_shoulder":"1080.72, 362.537, 0.856007","left_elbow":"974.769, 321.334, 0.862715","right_elbow":"1180.74, 362.383, 0.83656","left_wrist":"998.305, 271.283, 0.880511","right_wrist":"1189.55, 286.014, 0.878366","left_hip":"1001.2, 545.002, 0.726784","right_hip":"1068.82, 547.974, 0.748142","left_knee":"1001.27, 665.585, 0.848781","right_knee":"1072.01, 671.558, 0.878119","left_ankle":"1001.12, 768.664, 0.82031","right_ankle":"1071.97, 786.435, 0.879214","neck":"1036.51, 362.452, 0.886114","left_palm":"1189.55, 286.014, 0.878366","right_palm":"998.305, 271.283, 0.880511","back":"1030.71, 547.853, 0.71379","waist":"1030.71, 547.853, 0.71379","left_foot":"0, 0, 0","right_foot":"1115.95, 792.29, 0.535265"},"width":1920,"height":1080}}