{"info":{"frame":32,"view":1,"img_key":"C:\\furun\\furun_second\\img\\Back_lunge_A_cam1_32.png","name":"Back_lunge","standing":0,"pose":1,"grip":1,"e_point":"Hip, Leg","index":32,"conditions":"A","desc":"Stand with your feet shoulder width and place the bar (with tension) on your upper traps behind the neck.","bones":{"nose":"0, 0, 0","left_eye":"556.97, 400.213, 0.0575545","right_eye":"0, 0, 0","left_ear":"560.793, 398.252, 0.677555","right_ear":"588.277, 370.789, 0.0510763","left_shoulder":"584.313, 400.171, 0.856011","right_shoulder":"637.201, 384.456, 0.851957","left_elbow":"578.482, 443.226, 0.858298","right_elbow":"692.067, 411.871, 0.86191","left_wrist":"541.276, 419.778, 0.856549","right_wrist":"662.715, 386.453, 0.716329","left_hip":"656.836, 484.374, 0.672141","right_hip":"697.884, 478.464, 0.772138","left_knee":"601.849, 482.493, 0.807584","right_knee":"692.067, 552.985, 0.770633","left_ankle":"623.527, 564.725, 0.739582","right_ankle":"746.956, 592.185, 0.795066","neck":"607.876, 394.319, 0.814845","left_palm":"662.715, 386.453, 0.716329","right_palm":"541.276, 419.778, 0.856549","back":"678.378, 480.471, 0.738879","waist":"678.378, 480.471, 0.738879","left_foot":"590.226, 560.804, 0.533","right_foot":"746.899, 631.35, 0.707867"},"width":1920,"height":1080}}