{"info":{"frame":4,"view":1,"img_key":"C:\\furun\\furun_second\\img\\Back_lunge_A_cam1_04.png","name":"Back_lunge","standing":0,"pose":1,"grip":1,"e_point":"Hip, Leg","index":4,"conditions":"A","desc":"Stand with your feet shoulder width and place the bar (with tension) on your upper traps behind the neck.","bones":{"nose":"0, 0, 0","left_eye":"0, 0, 0","right_eye":"0, 0, 0","left_ear":"621.553, 227.788, 0.938711","right_ear":"662.651, 225.774, 0.434704","left_shoulder":"619.659, 272.834, 0.885722","right_shoulder":"684.204, 264.952, 0.839809","left_elbow":"599.927, 325.769, 0.857772","right_elbow":"711.692, 313.967, 0.905441","left_wrist":"582.34, 286.453, 0.832649","right_wrist":"709.639, 270.834, 0.796867","left_hip":"633.216, 396.248, 0.757938","right_hip":"670.529, 390.347, 0.704229","left_knee":"627.396, 480.483, 0.799344","right_knee":"668.535, 472.677, 0.847132","left_ankle":"627.395, 558.826, 0.812845","right_ankle":"672.49, 547.114, 0.75114","neck":"650.985, 270.854, 0.897884","left_palm":"709.639, 270.834, 0.796867","right_palm":"582.34, 286.453, 0.832649","back":"650.925, 394.276, 0.777778","waist":"650.925, 394.276, 0.777778","left_foot":"599.968, 558.87, 0.619286","right_foot":"650.881, 547.078, 0.450334"},"width":1920,"height":1080}}